README.md
setup.py
setup_gui.py
http_proxy_gui.egg-info/PKG-INFO
http_proxy_gui.egg-info/SOURCES.txt
http_proxy_gui.egg-info/dependency_links.txt
http_proxy_gui.egg-info/entry_points.txt
http_proxy_gui.egg-info/requires.txt
http_proxy_gui.egg-info/top_level.txt
proxycore/__init__.py
proxygui/__init__.py
proxygui/main.py
proxygui/main_window.py
proxygui/worker.py
proxygui/plugins/__init__.py
proxygui/plugins/abstract_plugins.py
proxygui/plugins/cmd_plugin.py
proxygui/plugins/code_gen_plugin.py
proxygui/plugins/core_plugin.py
proxygui/plugins/plugin_registry.py
proxygui/plugins/request_plugin.py
proxygui/plugins/soap_plugin.py
proxygui/plugins/soap/SoapCodeGenerator.py
proxygui/plugins/soap/__init__.py
proxygui/widgets/__init__.py
proxygui/widgets/body_content_viewer.py
proxygui/widgets/connection_config.py
proxygui/widgets/http_messages_tabs.py
proxygui/widgets/http_messages_tree_view.py
proxygui/widgets/top_tabs.py
test/test_dispatcher.py
test/test_flow_definition.py
test/test_http_parser.py
test/test_persistence.py
test/test_soap_matcher.py
test/test_soap_transform.py
test/test_transform.py