Metadata-Version: 1.0
Name: http-proxy-gui
Version: 1.0.11
Summary: HTTP reverse proxy for debugging and packet manipulation - GUI
Home-page: https://github.com/xRodney/pyproxy
Author: Dusan Jakub
Author-email: UNKNOWN
License: UNKNOWN
Platform: UNKNOWN
